astro_ph/__init__.py
astro_ph/apps/__init__.py
astro_ph/apps/slack.py
astro_ph/article.py
astro_ph/cli.py
astro_ph/constants.py
astro_ph/detex.py
astro_ph/search.py
astro_ph/translate.py
astro_ph-0.3.1.dist-info/entry_points.txt
astro_ph-0.3.1.dist-info/LICENSE
astro_ph-0.3.1.dist-info/WHEEL
astro_ph-0.3.1.dist-info/METADATA
astro_ph-0.3.1.dist-info/RECORD
