Metadata-Version: 2.1
Name: astro-ph
Version: 0.3.1
Summary: Translate and post arXiv articles to various apps
Home-page: https://github.com/astropenguin/astro-ph/
License: MIT
Keywords: arxiv,astro-ph,translation
Author: Akio Taniguchi
Author-email: taniguchi@a.phys.nagoya-u.ac.jp
Requires-Python: >=3.8,<4.0
Classifier: License :: OSI Approved :: MIT License
Classifier: Programming Language :: Python :: 3
Classifier: Programming Language :: Python :: 3.10
Classifier: Programming Language :: Python :: 3.8
Classifier: Programming Language :: Python :: 3.9
Requires-Dist: arxiv (>=1.4,<2.0)
Requires-Dist: dateparser (>=1.1,<2.0)
Requires-Dist: fire (>=0.4,<0.5)
Requires-Dist: playwright (>=1.16,<2.0)
Requires-Dist: requests (>=2.26,<3.0)
Requires-Dist: tomli (>=1.2,<2.0)
Project-URL: Documentation, https://astropenguin.github.io/astro-ph/
